pyrpc/__init__.py
pyrpc/__main__.py
pyrpc/classmodule.py
pyrpc/funcmodule.py
pyrpc_discord-1.1.3.dist-info/LICENSE
pyrpc_discord-1.1.3.dist-info/METADATA
pyrpc_discord-1.1.3.dist-info/WHEEL
pyrpc_discord-1.1.3.dist-info/entry_points.txt
pyrpc_discord-1.1.3.dist-info/top_level.txt
pyrpc_discord-1.1.3.dist-info/RECORD
